fast5seek/__init__.py
fast5seek/cli.py
fast5seek/fast5seek.py
fast5seek/fast5seek_parallelized.py
fast5seek-0.1.1.dist-info/METADATA
fast5seek-0.1.1.dist-info/RECORD
fast5seek-0.1.1.dist-info/WHEEL
fast5seek-0.1.1.dist-info/entry_points.txt
fast5seek-0.1.1.dist-info/top_level.txt
