Metadata-Version: 2.1
Name: fast5seek
Version: 0.1.1
Summary: Get paths for fast5 files contained in BAM, SAM, or fastq.
Home-page: https://github.com/mbhall88/fast5seek
Author: Michael Hall
Author-email: mbhall88@gmail.com
License: MIT license
Keywords: fast5seek
Platform: UNKNOWN
Classifier: License :: OSI Approved :: MIT License
Classifier: Natural Language :: English
Classifier: Programming Language :: Python :: 3.5
Classifier: Programming Language :: Python :: 3.6
Classifier: Programming Language :: Python :: 3.7
Requires-Dist: ont-fast5-api
Requires-Dist: pysam
